asilib/__init__.py
asilib/__main__.py
asilib/conjunction.py
asilib/imager.py
asilib/imagers.py
asilib/map.py
asilib/skymap.py
asilib/utils.py
asilib/analysis/__init__.py
asilib/analysis/equal_area.py
asilib/analysis/keogram.py
asilib/analysis/map.py
asilib/analysis/start_generator.py
asilib/asi/__init__.py
asilib/asi/fake_asi.py
asilib/asi/lamp_phantom.py
asilib/asi/psa_emccd.py
asilib/asi/rego.py
asilib/asi/themis.py
asilib/asi/trex.py
asilib/data/asi_locations.csv
asilib/data/ne_10m_land.zip
asilib/examples/__init__.py
asilib/io/__init__.py
asilib/io/download.py
asilib/io/load.py
asilib/io/utils.py
asilib/plot/__init__.py
asilib/plot/animate_fisheye.py
asilib/plot/animate_map.py
asilib/plot/plot_fisheye.py
asilib/plot/plot_keogram.py
asilib/plot/plot_map.py
asilib/plot/utils.py
asilib/tests/__init__.py
asilib/tests/mock_footprint.py
asilib/tests/test_conjunction.py
asilib/tests/test_downloader.py
asilib/tests/test_imager.py
asilib/tests/test_imagers.py
asilib/tests/test_map.py
asilib/tests/test_rego.py
asilib/tests/test_skymap.py
asilib/tests/test_themis.py
asilib/tests/test_trex.py
asilib/tests/test_utils.py
aurora_asi_lib-0.21.1.dist-info/LICENSE
aurora_asi_lib-0.21.1.dist-info/METADATA
aurora_asi_lib-0.21.1.dist-info/WHEEL
aurora_asi_lib-0.21.1.dist-info/top_level.txt
aurora_asi_lib-0.21.1.dist-info/RECORD
