Metadata-Version: 2.1
Name: aurora-asi-lib
Version: 0.21.1
Summary: An open source package providing data access and analysis tools for the world's all-sky imager (ASI) data.
Author-email: Mykhaylo Shumko <msshumko@gmail.com>
Project-URL: Homepage, https://aurora-asi-lib.readthedocs.io/
Project-URL: Documentation, https://aurora-asi-lib.readthedocs.io/
Project-URL: Source, https://github.com/mshumko/aurora-asi-lib
Project-URL: Issues, https://github.com/mshumko/aurora-asi-lib/issues
Project-URL: Changelog, https://github.com/mshumko/aurora-asi-lib/blob/main/CHANGELOG.md
Keywords: aurora,all sky imager,REGO,THEMIS,TREx
Classifier: License :: OSI Approved :: GNU General Public License v3 (GPLv3)
Classifier: Programming Language :: Python :: 3
Classifier: Programming Language :: Python :: 3.9
Classifier: Programming Language :: Python :: 3.10
Classifier: Programming Language :: Python :: 3.11
Classifier: Programming Language :: Python :: 3.12
License-File: LICENSE
Requires-Dist: wheel
Requires-Dist: beautifulsoup4
Requires-Dist: requests
Requires-Dist: numpy <2.0
Requires-Dist: scipy >=1.10.0
Requires-Dist: pandas
Requires-Dist: matplotlib <4.0,>=3.7
Requires-Dist: cdflib >=0.3.20
Requires-Dist: ffmpeg-python
Requires-Dist: pymap3d
Requires-Dist: aacgmv2
Requires-Dist: pyshp >=2.3
Requires-Dist: rego-imager-readfile <2.0,>=1.2.0
Requires-Dist: themis-imager-readfile <2.0,>=1.2.1
Requires-Dist: trex-imager-readfile <2.0,>=1.5.1
Requires-Dist: opencv-python <5.0,>=4.8.0
